LICENSE
MANIFEST.in
README
setup.py
gurumate/__init__.py
gurumate/base.py
gurumate/httpd.py
gurumate/networking.py
gurumate/web.py
gurumate.egg-info/PKG-INFO
gurumate.egg-info/SOURCES.txt
gurumate.egg-info/dependency_links.txt
gurumate.egg-info/not-zip-safe
gurumate.egg-info/requires.txt
gurumate.egg-info/top_level.txt
gurumate/exceptions/__init__.py
gurumate/exceptions/base.py
gurumate/linux2/__init__.py
gurumate/linux2/apache.py
gurumate/linux2/apt.py
gurumate/linux2/files.py
gurumate/linux2/mysql.py
gurumate/linux2/procs.py
gurumate/linux2/user.py
gurumate/win32/__init__.py
gurumate/win32/win.py