Metadata-Version: 1.1
Name: gurumate
Version: 2.8.6
Summary: A library of platform-independent tools that ease gathering information about the system.
Home-page: http://confluence.cloud9ers.com/display/TGILA/Gurumate+SDK
Author: Cloud Niners Ltd.
Author-email: support@cloud9ers.com
License: LGPLv3
Platform: UNKNOWN
Classifier: Development Status :: 5 - Production/Stable
Classifier: Intended Audience :: Developers
Classifier: License :: OSI Approved :: GNU Lesser General Public License v3 (LGPLv3)
Classifier: Operating System :: Microsoft :: Windows :: Windows 7
Classifier: Operating System :: POSIX :: Linux
Classifier: Programming Language :: Python :: 2.6
Classifier: Programming Language :: Python :: 2.7
Classifier: Topic :: Software Development :: Libraries :: Application Frameworks
